MANIFEST.in
README.md
instapaper.py
setup.py
instapaper.egg-info/PKG-INFO
instapaper.egg-info/SOURCES.txt
instapaper.egg-info/dependency_links.txt
instapaper.egg-info/requires.txt
instapaper.egg-info/top_level.txt