Metadata-Version: 2.1
Name: instapaper
Version: 0.5
Summary: Unofficial Instapaper Python API.
Home-page: http://github.com/rsgalloway/instapaper
Author: Ryan Galloway
Author-email: ryan@rsgalloway.com
Requires-Dist: oauth2>=1.9.0.post1
